sartorius/__init__.py
sartorius/driver.py
sartorius/mock.py
sartorius/py.typed
sartorius/util.py
sartorius-0.7.0.dist-info/licenses/LICENSE
sartorius-0.7.0.dist-info/METADATA
sartorius-0.7.0.dist-info/WHEEL
sartorius-0.7.0.dist-info/entry_points.txt
sartorius-0.7.0.dist-info/top_level.txt
sartorius-0.7.0.dist-info/RECORD
