Metadata-Version: 2.4
Name: sartorius
Version: 0.7.0
Summary: Python driver for Sartorius and Minebea Intec scales.
Author-email: Pat Fuller <patrickfuller@gmail.com>
Maintainer-email: Alex Ruddick <alex@ruddick.tech>
License-Expression: GPL-2.0-or-later
Project-URL: Homepage, https://github.com/alexrudd2/sartorius/
Project-URL: Issues, https://github.com/alexrudd2/sartorius/issues
Classifier: Development Status :: 4 - Beta
Classifier: Natural Language :: English
Classifier: Programming Language :: Python
Classifier: Programming Language :: Python :: 3
Classifier: Programming Language :: Python :: 3.10
Classifier: Programming Language :: Python :: 3.11
Classifier: Programming Language :: Python :: 3.12
Classifier: Programming Language :: Python :: 3.13
Classifier: Programming Language :: Python :: 3.14
Classifier: Topic :: Scientific/Engineering :: Human Machine Interfaces
Classifier: Topic :: Scientific/Engineering :: Electronic Design Automation (EDA)
License-File: LICENSE
Requires-Dist: pyserial
Dynamic: license-file
